README.md
licence.txt
setup.py
pro_video_Ferramentas_teste_inicial.egg-info/PKG-INFO
pro_video_Ferramentas_teste_inicial.egg-info/SOURCES.txt
pro_video_Ferramentas_teste_inicial.egg-info/dependency_links.txt
pro_video_Ferramentas_teste_inicial.egg-info/top_level.txt
pro_video_ferramentas/__init__.py
pro_video_ferramentas/camera.py
pro_video_ferramentas/video.py