Metadata-Version: 2.1
Name: pro-video-Ferramentas-teste-inicial
Version: 1.0
Summary: Este pacote fornecerá ferramentas de processamento de vídeo
Author: Lucas
Author-email: lucas.edu.leme@hotmail.com
Keywords: camera,video,processamento
License-File: licence.txt
